vertebrae/__init__.py
vertebrae/config.py
vertebrae/core.py
vertebrae/database.py
vertebrae/service.py
vertebrae/cloud/__init__.py
vertebrae/cloud/aws.py
vertebrae/stores/__init__.py
vertebrae/stores/cache.py
vertebrae/stores/directory.py
vertebrae/stores/relational.py
vertebrae/stores/s3.py
vertebrae-0.6.13.dist-info/LICENSE
vertebrae-0.6.13.dist-info/METADATA
vertebrae-0.6.13.dist-info/WHEEL
vertebrae-0.6.13.dist-info/top_level.txt
vertebrae-0.6.13.dist-info/RECORD
