Metadata-Version: 2.1
Name: vertebrae
Version: 0.6.13
Summary: A security-focused app framework for async Python micro services
Author: privateducky
Author-email: coldduck@protonmail.com
Classifier: Programming Language :: Python :: 3
Classifier: License :: OSI Approved :: MIT License
Classifier: Operating System :: OS Independent
Requires-Python: >=3.8
License-File: LICENSE
Requires-Dist: aiohttp (==3.8.3)
Requires-Dist: aiohttp-session (==2.11.0)
Requires-Dist: psycopg2-binary (==2.9.3)
Requires-Dist: pyyaml (==6.0)
Requires-Dist: aioredis (~=2.0.1)
Requires-Dist: aiopg (~=1.3.4)
Requires-Dist: aiofiles (~=0.8.0)
Requires-Dist: aiobotocore (~=2.4.0)
Requires-Dist: botocore (~=1.27.9)
Requires-Dist: detect-probe (==0.9.26)
Requires-Dist: Jinja2 (~=3.1.2)
Requires-Dist: aiohttp-jinja2 (==1.5)
Requires-Dist: aiohttp-cors (==0.7.0)
